odoo/addons/stock_package_type_volume/README.rst
odoo/addons/stock_package_type_volume/__init__.py
odoo/addons/stock_package_type_volume/__manifest__.py
odoo/addons/stock_package_type_volume/i18n/it.po
odoo/addons/stock_package_type_volume/i18n/stock_package_type_volume.pot
odoo/addons/stock_package_type_volume/models/__init__.py
odoo/addons/stock_package_type_volume/models/stock_package_type.py
odoo/addons/stock_package_type_volume/readme/CONTRIBUTORS.md
odoo/addons/stock_package_type_volume/readme/DESCRIPTION.md
odoo/addons/stock_package_type_volume/static/description/icon.png
odoo/addons/stock_package_type_volume/static/description/index.html
odoo/addons/stock_package_type_volume/tests/__init__.py
odoo/addons/stock_package_type_volume/tests/test_stock_package_type_volume.py
odoo/addons/stock_package_type_volume/views/stock_package_type_views.xml
odoo_addon_stock_package_type_volume-18.0.1.0.0.2.dist-info/METADATA
odoo_addon_stock_package_type_volume-18.0.1.0.0.2.dist-info/WHEEL
odoo_addon_stock_package_type_volume-18.0.1.0.0.2.dist-info/top_level.txt
odoo_addon_stock_package_type_volume-18.0.1.0.0.2.dist-info/RECORD
